[
  {
    "id": "wood-1",
    "no": 1,
    "specification": "MAHOGANY - 30 UP",
    "woodName": "MAHOGANY",
    "pricePerM3Buyer": 2640000,
    "priceSafetyFactorBuyer": 264000,
    "buyerTotalPerM3": 2904000,
    "pricePerM3Supplier": 2350000,
    "invoiceCostPerM3": 14000666.666666666,
    "materialType": "kayu",
    "aktif": true
  },
  {
    "id": "wood-2",
    "no": 2,
    "specification": "MAHOGANY - 40 UP",
    "woodName": "MAHOGANY",
    "pricePerM3Buyer": 2805000,
    "priceSafetyFactorBuyer": 280500,
    "buyerTotalPerM3": 3085500,
    "pricePerM3Supplier": 2590000,
    "invoiceCostPerM3": 14787166.666666666,
    "materialType": "kayu",
    "aktif": true
  },
  {
    "id": "wood-3",
    "no": 3,
    "specification": "MAHOGANY - 50 UP",
    "woodName": "MAHOGANY",
    "pricePerM3Buyer": 3300000.0000000005,
    "priceSafetyFactorBuyer": 330000.00000000006,
    "buyerTotalPerM3": 3630000.0000000005,
    "pricePerM3Supplier": 2860000,
    "invoiceCostPerM3": 17146666.66666667,
    "materialType": "kayu",
    "aktif": true
  },
  {
    "id": "wood-4",
    "no": 4,
    "specification": "MAHOGANY - 60 UP",
    "woodName": "MAHOGANY",
    "pricePerM3Buyer": 5000000,
    "priceSafetyFactorBuyer": 500000,
    "buyerTotalPerM3": 5500000,
    "pricePerM3Supplier": 4500000,
    "invoiceCostPerM3": 25250000.000000004,
    "materialType": "kayu",
    "aktif": true
  },
  {
    "id": "wood-5",
    "no": 5,
    "specification": "TEAK TPK - 30 UP",
    "woodName": "TEAK TPK",
    "pricePerM3Buyer": 11500000,
    "priceSafetyFactorBuyer": 1150000,
    "buyerTotalPerM3": 12650000,
    "pricePerM3Supplier": 10000000,
    "invoiceCostPerM3": 56233333.333333336,
    "materialType": "kayu",
    "aktif": true
  },
  {
    "id": "wood-6",
    "no": 6,
    "specification": "TEAK TPK - 40 UP",
    "woodName": "TEAK TPK",
    "pricePerM3Buyer": 12500000,
    "priceSafetyFactorBuyer": 1250000,
    "buyerTotalPerM3": 13750000,
    "pricePerM3Supplier": 11500000,
    "invoiceCostPerM3": 61000000,
    "materialType": "kayu",
    "aktif": true
  },
  {
    "id": "wood-7",
    "no": 7,
    "specification": "TEAK KAMPUNG - 30 UP",
    "woodName": "TEAK KAMPUNG",
    "pricePerM3Buyer": 5500000,
    "priceSafetyFactorBuyer": 550000,
    "buyerTotalPerM3": 6050000,
    "pricePerM3Supplier": 5100000,
    "invoiceCostPerM3": 27633333.333333336,
    "materialType": "kayu",
    "aktif": true
  },
  {
    "id": "wood-8",
    "no": 8,
    "specification": "TEAK KAMPUNG - 40 UP",
    "woodName": "TEAK KAMPUNG",
    "pricePerM3Buyer": 6710000.000000001,
    "priceSafetyFactorBuyer": 671000.0000000001,
    "buyerTotalPerM3": 7381000.000000001,
    "pricePerM3Supplier": 6200000,
    "invoiceCostPerM3": 33401000.000000004,
    "materialType": "kayu",
    "aktif": true
  },
  {
    "id": "wood-9",
    "no": 9,
    "specification": "MANGGA - 30 UP",
    "woodName": "MANGGA",
    "pricePerM3Buyer": 1012000.0000000001,
    "priceSafetyFactorBuyer": 101200.00000000001,
    "buyerTotalPerM3": 1113200.0000000002,
    "pricePerM3Supplier": 770000,
    "invoiceCostPerM3": 6982666.666666668,
    "materialType": "kayu",
    "aktif": true
  },
  {
    "id": "wood-10",
    "no": 10,
    "specification": "TEAK KAMPUNG - 20 UP",
    "woodName": "TEAK KAMPUNG",
    "pricePerM3Buyer": 3750000,
    "priceSafetyFactorBuyer": 375000,
    "buyerTotalPerM3": 4125000,
    "pricePerM3Supplier": 3500000,
    "invoiceCostPerM3": 19291666.666666668,
    "materialType": "kayu",
    "aktif": true
  },
  {
    "id": "wood-11",
    "no": 11,
    "specification": "MINDI - 30 UP 200",
    "woodName": "MINDI",
    "pricePerM3Buyer": 2850000,
    "priceSafetyFactorBuyer": 285000,
    "buyerTotalPerM3": 3135000,
    "pricePerM3Supplier": 2640000,
    "invoiceCostPerM3": 17091666.666666668,
    "materialType": "kayu",
    "aktif": true
  },
  {
    "id": "wood-12",
    "no": 12,
    "specification": "MINDI - 40 UP 200",
    "woodName": "MINDI",
    "pricePerM3Buyer": 3050000,
    "priceSafetyFactorBuyer": 305000,
    "buyerTotalPerM3": 3355000,
    "pricePerM3Supplier": 2805000,
    "invoiceCostPerM3": 18191666.666666668,
    "materialType": "kayu",
    "aktif": true
  },
  {
    "id": "wood-13",
    "no": 13,
    "specification": "MINDI - 50 UP 200",
    "woodName": "MINDI",
    "pricePerM3Buyer": 3500000,
    "priceSafetyFactorBuyer": 350000,
    "buyerTotalPerM3": 3850000,
    "pricePerM3Supplier": 3300000.0000000005,
    "invoiceCostPerM3": 20666666.666666668,
    "materialType": "kayu",
    "aktif": true
  },
  {
    "id": "wood-14",
    "no": 14,
    "specification": "TEAK KAMPUNG - 20 UP 150",
    "woodName": "TEAK KAMPUNG",
    "pricePerM3Buyer": 3190000,
    "priceSafetyFactorBuyer": 319000,
    "buyerTotalPerM3": 3509000,
    "pricePerM3Supplier": 2900000,
    "invoiceCostPerM3": 16622333.333333334,
    "materialType": "kayu",
    "aktif": true
  },
  {
    "id": "wood-15",
    "no": 15,
    "specification": "TEAK KAMPUNG - 20 UP 200",
    "woodName": "TEAK KAMPUNG",
    "pricePerM3Buyer": 3410000,
    "priceSafetyFactorBuyer": 341000,
    "buyerTotalPerM3": 3751000,
    "pricePerM3Supplier": 3100000,
    "invoiceCostPerM3": 17671000.000000004,
    "materialType": "kayu",
    "aktif": true
  },
  {
    "id": "wood-16",
    "no": 16,
    "specification": "TEAK KAMPUNG - 20 UP 250",
    "woodName": "TEAK KAMPUNG",
    "pricePerM3Buyer": 3630000,
    "priceSafetyFactorBuyer": 363000,
    "buyerTotalPerM3": 3993000,
    "pricePerM3Supplier": 3300000,
    "invoiceCostPerM3": 18719666.666666668,
    "materialType": "kayu",
    "aktif": true
  },
  {
    "id": "wood-19",
    "no": 19,
    "specification": "TEAK KAMPUNG - 30 UP 150",
    "woodName": "TEAK KAMPUNG",
    "pricePerM3Buyer": 4500000,
    "priceSafetyFactorBuyer": 450000,
    "buyerTotalPerM3": 4950000,
    "pricePerM3Supplier": 4500000,
    "invoiceCostPerM3": 22866666.666666668,
    "materialType": "kayu",
    "aktif": true
  },
  {
    "id": "wood-20",
    "no": 20,
    "specification": "TEAK KAMPUNG - 30 UP 200",
    "woodName": "TEAK KAMPUNG",
    "pricePerM3Buyer": 5000000,
    "priceSafetyFactorBuyer": 500000,
    "buyerTotalPerM3": 5500000,
    "pricePerM3Supplier": 5000000,
    "invoiceCostPerM3": 25250000.000000004,
    "materialType": "kayu",
    "aktif": true
  },
  {
    "id": "wood-21",
    "no": 21,
    "specification": "TEAK KAMPUNG - 30 UP 250",
    "woodName": "TEAK KAMPUNG",
    "pricePerM3Buyer": 5500000,
    "priceSafetyFactorBuyer": 550000,
    "buyerTotalPerM3": 6050000,
    "pricePerM3Supplier": 5500000,
    "invoiceCostPerM3": 27633333.333333336,
    "materialType": "kayu",
    "aktif": true
  },
  {
    "id": "wood-22",
    "no": 22,
    "specification": "TEAK KAMPUNG - 30 UP 300",
    "woodName": "TEAK KAMPUNG",
    "pricePerM3Buyer": 6000000,
    "priceSafetyFactorBuyer": 600000,
    "buyerTotalPerM3": 6600000,
    "pricePerM3Supplier": 6000000,
    "invoiceCostPerM3": 30016666.666666668,
    "materialType": "kayu",
    "aktif": true
  },
  {
    "id": "wood-25",
    "no": 25,
    "specification": "TEAK KAMPUNG - 40 UP 200",
    "woodName": "TEAK KAMPUNG",
    "pricePerM3Buyer": 6000000,
    "priceSafetyFactorBuyer": 600000,
    "buyerTotalPerM3": 6600000,
    "pricePerM3Supplier": 6000000,
    "invoiceCostPerM3": 30016666.666666668,
    "materialType": "kayu",
    "aktif": true
  },
  {
    "id": "wood-26",
    "no": 26,
    "specification": "TEAK KAMPUNG - 40 UP 250",
    "woodName": "TEAK KAMPUNG",
    "pricePerM3Buyer": 6500000,
    "priceSafetyFactorBuyer": 650000,
    "buyerTotalPerM3": 7150000,
    "pricePerM3Supplier": 6500000,
    "invoiceCostPerM3": 32400000.000000004,
    "materialType": "kayu",
    "aktif": true
  },
  {
    "id": "wood-27",
    "no": 27,
    "specification": "TEAK KAMPUNG - 40 UP 300",
    "woodName": "TEAK KAMPUNG",
    "pricePerM3Buyer": 7000000,
    "priceSafetyFactorBuyer": 700000,
    "buyerTotalPerM3": 7700000,
    "pricePerM3Supplier": 7000000,
    "invoiceCostPerM3": 34783333.33333333,
    "materialType": "kayu",
    "aktif": true
  }
]